{"dataset": {"id": 10095370, "dataset_code": "AFX_X", "database_code": "FSE", "name": "Carl Zeiss Meditec (AFX_X)", "description": "Stock Prices for Carl Zeiss Meditec (2020-11-02) from the Frankfurt Stock Exchange.<br><br>Trading System: Xetra<br><br>ISIN: DE0005313704", "refreshed_at": "2020-12-01T14:48:09.907Z", "newest_available_date": "2020-12-01", "oldest_available_date": "2000-06-07", "column_names": ["Date", "Open", "High", "Low", "Close", "Change", "Traded Volume", "Turnover", "Last Price of the Day", "Daily Traded Units", "Daily Turnover"], "frequency": "daily", "type": "Time Series", "premium": false, "limit": null, "transform": null, "column_index": null, "start_date": "2017-07-01", "end_date": "2017-07-31", "data": [["2017-07-31", 44.94, 45.75, 44.94, 45.3, null, 62672.0, 2844210.0, null, null, null], ["2017-07-28", 45.26, 45.29, 44.75, 44.97, null, 114006.0, 5127247.0, null, null, null], ["2017-07-27", 45.16, 45.45, 45.15, 45.25, null, 50557.0, 2290284.0, null, null, null], ["2017-07-26", 44.91, 45.33, 44.46, 45.16, null, 81970.0, 3688510.0, null, null, null], ["2017-07-25", 44.7, 45.04, 44.63, 44.82, null, 112224.0, 5033312.0, null, null, null], ["2017-07-24", 45.31, 45.31, 44.49, 44.61, null, 104282.0, 4661866.0, null, null, null], ["2017-07-21", 45.57, 45.88, 45.04, 45.44, null, 73422.0, 3334695.0, null, null, null], ["2017-07-20", 45.74, 45.96, 45.23, 45.66, null, 87399.0, 3986488.0, null, null, null], ["2017-07-19", 45.06, 45.72, 44.94, 45.57, null, 71971.0, 3273001.0, null, null, null], ["2017-07-18", 45.5, 45.55, 44.7, 45.0, null, 104003.0, 4684627.0, null, null, null], ["2017-07-17", 45.6, 46.23, 45.29, 45.6, null, 104995.0, 4801806.0, null, null, null], ["2017-07-14", 45.07, 45.56, 44.83, 45.53, null, 67375.0, 3054060.0, null, null, null], ["2017-07-13", 44.67, 45.18, 44.67, 44.95, null, 82745.0, 3718928.0, null, null, null], ["2017-07-12", 44.29, 45.05, 43.89, 44.95, null, 115705.0, 5133971.0, null, null, null], ["2017-07-11", 44.94, 44.94, 44.08, 44.2, null, 90538.0, 4010457.0, null, null, null], ["2017-07-10", 44.64, 45.18, 44.51, 44.7, null, 71868.0, 3221218.0, null, null, null], ["2017-07-07", 44.79, 44.79, 44.25, 44.53, null, 47999.0, 2136578.0, null, null, null], ["2017-07-06", 45.5, 45.5, 44.15, 44.62, null, 66116.0, 2952605.0, null, null, null], ["2017-07-05", 44.67, 45.36, 44.44, 45.19, null, 48706.0, 2189436.0, null, null, null], ["2017-07-04", 45.83, 45.83, 44.74, 44.8, null, 50549.0, 2273551.0, null, null, null], ["2017-07-03", 45.29, 45.83, 45.06, 45.75, null, 71381.0, 3251502.0, null, null, null]], "collapse": "daily", "order": null, "database_id": 6129}}